DelimiterFinder/__init__.py
DelimiterFinder/bayes.py
DelimiterFinder/finder.py
DelimiterFinder-0.0.4.dist-info/LICENSE
DelimiterFinder-0.0.4.dist-info/METADATA
DelimiterFinder-0.0.4.dist-info/WHEEL
DelimiterFinder-0.0.4.dist-info/top_level.txt
DelimiterFinder-0.0.4.dist-info/RECORD
