Metadata-Version: 2.1
Name: DelimiterFinder
Version: 0.0.4
Summary: Python package for probabilistic delimiter detection.
Home-page: https://github.com/harjotsodhi/DelimiterFinder
Author: Harjot Sodhi
Author-email: harjotsodhi17@gmail.com
License: UNKNOWN
Platform: UNKNOWN
Classifier: Programming Language :: Python :: 3
Classifier: Programming Language :: Python :: 3.6
Classifier: Programming Language :: Python :: 3.7
Classifier: Programming Language :: Python :: 3.8
Classifier: Programming Language :: Python :: 3.9
Classifier: Programming Language :: Python :: 3.10
Classifier: Operating System :: OS Independent
Classifier: License :: OSI Approved :: GNU General Public License v3 or later (GPLv3+)
License-File: LICENSE
